panti/__init__.py
panti/__main__.py
panti/py.typed
panti/vallaris.py
panti-0.0.1.dist-info/LICENSE
panti-0.0.1.dist-info/METADATA
panti-0.0.1.dist-info/WHEEL
panti-0.0.1.dist-info/entry_points.txt
panti-0.0.1.dist-info/RECORD
