Metadata-Version: 2.1
Name: panti
Version: 0.0.1
Summary: Panti
Home-page: https://github.com/wasdee/panti
License: MIT
Author: Nutchanon Ninyawee
Author-email: me@nutchanon.org
Requires-Python: >=3.7,<4.0
Classifier: Development Status :: 4 - Beta
Classifier: License :: OSI Approved :: MIT License
Classifier: Programming Language :: Python :: 3
Classifier: Programming Language :: Python :: 3.7
Classifier: Programming Language :: Python :: 3.8
Classifier: Programming Language :: Python :: 3.9
Classifier: Programming Language :: Python :: 3.10
Classifier: Programming Language :: Python :: 3.11
Requires-Dist: click (>=8.0.1)
Project-URL: Changelog, https://github.com/wasdee/panti/releases
Project-URL: Documentation, https://panti.readthedocs.io
Project-URL: Repository, https://github.com/wasdee/panti
